lib_holdings/__init__.py
lib_holdings/__main__.py
lib_holdings/api.py
lib_holdings-2.0.0.dist-info/LICENSE
lib_holdings-2.0.0.dist-info/METADATA
lib_holdings-2.0.0.dist-info/WHEEL
lib_holdings-2.0.0.dist-info/entry_points.txt
lib_holdings-2.0.0.dist-info/RECORD
