Metadata-Version: 2.1
Name: lib-holdings
Version: 2.0.0
Summary: CLI tool for retrieving holding counts for a list of OCNs and libraries
Home-page: https://github.com/ubvu/lib-holdings
License: MIT
Author: Max Paulus
Requires-Python: >=3.8,<4.0
Classifier: License :: OSI Approved :: MIT License
Classifier: Programming Language :: Python :: 3
Classifier: Programming Language :: Python :: 3.8
Classifier: Programming Language :: Python :: 3.9
Classifier: Programming Language :: Python :: 3.10
Classifier: Programming Language :: Python :: 3.11
Classifier: Programming Language :: Python :: 3.12
Requires-Dist: click (>=8.1.3,<9.0.0)
Requires-Dist: pandas (>=1.4.2,<2.0.0)
Requires-Dist: requests (>=2.27.1,<3.0.0)
Requires-Dist: requests-oauthlib (>=1.3.1,<2.0.0)
Project-URL: Repository, https://github.com/ubvu/lib-holdings
